[
    {
        "name": "Food log",
        "theme": "pink",
        "entries": [
            {
                "date": "1 mar",
                "text": "Food log drtfgh gyuuhjoiy"
            },
            {
                "date": "29 feb",
                "text": "Food log drtsd hjoiy"
            },
            {
                "date": "28 feb",
                "text": "Food loghj ihkj lik"
            },
            {
                "date": "27 feb",
                "text": "Food logfyjguhjk b gjh lk"
            }
        ]
    },
    {
        "name": "Health log",
        "theme": "green",
        "entries": [
            {
                "date": "1 mar",
                "text": "Health logOTHER SHIT"
            },
            {
                "date": "29 feb",
                "text": "Health logSHIT OTHER"
            },
            {
                "date": "28 feb",
                "text": "Health loghj ihkj lik"
            },
            {
                "date": "27 feb",
                "text": "Health logfyjguhjk b gjh lk"
            }
        ]
    },
    {
        "name": "Ideas log",
        "theme": "purple",
        "entries": [
            {
                "date": "13 jun",
                "text": "Ideas logBLAH"
            },
            {
                "date": "4 may",
                "text": "Ideas logBLAH"
            },
            {
                "date": "25 apr",
                "text": "Ideas loghj ihkj lik"
            },
            {
                "date": "1 mar",
                "text": "Ideas logfyjguhjk b gjh lk"
            },
            {
                "date": "14 jan",
                "text": "Ideas log1241342"
            },
            {
                "date": "13 jan",
                "text": "Ideas log1241342"
            },{
                "date": "12 jan",
                "text": "Ideas log1241342"
            },
            {
                "date": "11 jan",
                "text": "Ideas log1241342"
            },
            {
                "date": "10 jan",
                "text": "Ideas log1241342"
            },
            {
                "date": "9 jan",
                "text": "Ideas log1241342"
            },
            {
                "date": "8 jan",
                "text": "Ideas log1241342"
            },
            {
                "date": "7 jan",
                "text": "Ideas log1241342"
            }
        ]
    },
    {
        "name": "BULLSHIT LOG",
        "theme": "grey",
        "entries": [
            {
                "date": "30 oct",
                "text": "AAAAABULLSHIT LOG"
            },
            {
                "date": "17 oct",
                "text": "BULLSHITBULLSHIT LOG"
            },
            {
                "date": "16 oct",
                "text": "hj ihkj likBULLSHIT LOG"
            },
            {
                "date": "15 oct",
                "text": "fyjguhjk b gjh lkBULLSHIT LOG"
            }
        ]
    },
    {
        "name": "some yellow log",
        "theme": "yellow",
        "entries": [
            {
                "date": "1 mar",
                "text": "some yellow logellow"
            },
            {
                "date": "29 feb",
                "text": "some yellow logyellow"
            },
            {
                "date": "28 feb",
                "text": "some yellow loghj ihkj lik"
            },
            {
                "date": "27 feb",
                "text": "some yellow logfyjguhjk b gjh lk"
            }
        ]
    },
    {
        "name": "some pink log",
        "theme": "pink",
        "entries": [
            {
                "date": "1 mar",
                "text": "some PINK logellow"
            },
            {
                "date": "29 feb",
                "text": "some PINK logyellow"
            },
            {
                "date": "28 feb",
                "text": "some PINK loghj ihkj lik"
            },
            {
                "date": "27 feb",
                "text": "some PINK logfyjguhjk b gjh lk"
            }
        ]
    }
]
